hmin/__init__.py
hmin/__main__.py
hmin/base.py
hmin/decorators.py
hmin/middleware.py
hmin/tests/__init__.py
hmin/tests/conftest.py
hmin/tests/helpers.py
hmin/tests/test_base.py
hmin/tests/test_decorators.py
hmin/tests/test_general.py
hmin/tests/test_middleware_plain.py
hmin/tests/data/gazeta.html
hmin/tests/data/gazeta_min.html
hmin/tests/data/habrahabr.html
hmin/tests/data/habrahabr_min.html
hmin/tests/data/lenta.html
hmin/tests/data/lenta_min.html
hmin/tests/data/raiffeisen.html
hmin/tests/data/raiffeisen_min.html
hmin/tests/data/youtube.html
hmin/tests/data/youtube_min.html
django_hmin-0.5.4.dist-info/LICENSE
django_hmin-0.5.4.dist-info/WHEEL
django_hmin-0.5.4.dist-info/METADATA
django_hmin-0.5.4.dist-info/RECORD
