Metadata-Version: 2.1
Name: django-hmin
Version: 0.5.4
Summary: Html minification middleware with (but not only) django support and good
Home-page: https://github.com/xfenix/django-hmin/
License: UNKNOWN
Author: Denis Anikin
Author-email: ad@xfenix.ru
Requires-Python: >=3.7
Classifier: License :: OSI Approved :: MIT License
Classifier: Programming Language :: Python :: 3
Classifier: Programming Language :: Python :: 3.7
Classifier: Programming Language :: Python :: 3.8
Classifier: Programming Language :: Python :: 3.9
Classifier: Framework :: Django :: 2.1
Classifier: Framework :: Django :: 2.2
Classifier: Framework :: Django :: 3.0
Classifier: Framework :: Django :: 3.1
Classifier: Topic :: Software Development :: Libraries :: Python Modules
Project-URL: Documentation, https://github.com/xfenix/django-hmin/#django-hmin
